soopsocks/__init__.py
soopsocks/__main__.py
soopsocks/_autorun.exe
soopsocks/autostart.py
soopsocks/cli.py
soopsocks/config.py
soopsocks/discord.py
soopsocks/egress.py
soopsocks/firewall.py
soopsocks/server.py
soopsocks/service_windows.py
soopsocks-0.2.7.dist-info/licenses/LICENSE
soopsocks-0.2.7.dist-info/METADATA
soopsocks-0.2.7.dist-info/WHEEL
soopsocks-0.2.7.dist-info/entry_points.txt
soopsocks-0.2.7.dist-info/top_level.txt
soopsocks-0.2.7.dist-info/RECORD
