Metadata-Version: 2.4
Name: soopsocks
Version: 0.2.7
Summary: SOCKS5 server with Discord egress + Windows auto-start (service or scheduled task)
Author-email: Your Name <you@example.com>
Classifier: Programming Language :: Python :: 3
Classifier: License :: OSI Approved :: MIT License
Classifier: Operating System :: OS Independent
Requires-Python: >=3.9
License-File: LICENSE
Dynamic: license-file
